neutron_cinema.libs/libxerces-c-3-6c763fb7.2.so
neutron_cinema.libs/libNCrystal-6d79b556.so
neutron_cinema.libs/libmcpl-6920e294.so
neutron_cinema.libs/libfftw3-17cc48a2.so.3.3.2
neutron_cinema.libs/libhdf5-d8b2f36f.so.200.2.0
neutron_cinema.libs/libgomp-a34b3233.so.1.0.0
neutron_cinema-1.0.0.dist-info/WHEEL
neutron_cinema-1.0.0.dist-info/METADATA
neutron_cinema-1.0.0.dist-info/LICENSE
neutron_cinema-1.0.0.dist-info/RECORD
neutron_cinema-1.0.0.dist-info/top_level.txt
Cinema/hash.txt
Cinema/__init__.py
Cinema/libprompt_core.so
Cinema/gdml/totScat2022AllGeo.gdml
Cinema/gdml/mpi_detector.gdml
Cinema/gdml/child.gdml
Cinema/gdml/mother.gdml
Cinema/gdml/watersphere_bias.gdml
Cinema/gdml/simple_geo.gdml
Cinema/gdml/cubes.gdml
Cinema/gdml/first_geo.gdml
Cinema/gdml/chopper.gdml
Cinema/gdml/simple_geo_loop.gdml
Cinema/gdml/materials/single_crystal.gdml
Cinema/gdml/materials/materials.gdml
Cinema/gdml/volumes/box.gdml
Cinema/gdml/volumes/parallelepiped_bug.gdml
Cinema/gdml/volumes/sphere.gdml
Cinema/gdml/volumes/trapezoid.gdml
Cinema/gdml/volumes/arbitrary_trapezoid.gdml
Cinema/gdml/volumes/solid_union_bug.gdml
Cinema/gdml/volumes/extruded_solid_bug.gdml
Cinema/gdml/volumes/solid_subtraction_bug.gdml
Cinema/gdml/volumes/torus_bug.gdml
Cinema/gdml/volumes/ellipsoid_bug.gdml
Cinema/gdml/volumes/hyperbolic_tube.gdml
Cinema/gdml/volumes/solid_multiunion_bug.gdml
Cinema/gdml/volumes/scaled_solid_bug.gdml
Cinema/gdml/volumes/tetrahedron.gdml
Cinema/gdml/volumes/cone.gdml
Cinema/gdml/volumes/cutTube.gdml
Cinema/gdml/volumes/polyhedra.gdml
Cinema/gdml/volumes/general_trapezoid.gdml
Cinema/gdml/volumes/paraboloid.gdml
Cinema/gdml/volumes/tessellated_solid_bug.gdml
Cinema/gdml/volumes/tube.gdml
Cinema/gdml/volumes/orb.gdml
Cinema/gdml/volumes/polycone.gdml
Cinema/gdml/volumes/solid_intersection_bug.gdml
Cinema/gdml/publication/promptref/guide/guide_plot.py
Cinema/gdml/publication/promptref/guide/ScorerPSD_Monitor1_seed4096.mcpl.gz
Cinema/gdml/publication/promptref/guide/Monitor2_xy_1672190448.x_y
Cinema/gdml/publication/promptref/guide/README
Cinema/gdml/publication/promptref/guide/guide.gdml
