Metadata-Version: 2.1
Name: neutron-cinema
Version: 1.0.0
Summary: China Spallation Neutron Source Monte Carlo System
Author: Xiao-Xiao Cai, Ming Tang, Zi-Yi Pan, Ni Yang
Author-email: cinema-users@outlook.com
Project-URL: repository, https://gitlab.com/cinema-developers/prompt.git
Keywords: NCyrstal,Neutron Scattering,Spectroscopy
Classifier: Development Status :: 4 - Beta
Classifier: Intended Audience :: Science/Research
Classifier: Topic :: Scientific/Engineering :: Physics
Classifier: License :: OSI Approved
Classifier: Programming Language :: Python :: 3.7
Classifier: Programming Language :: Python :: 3.8
Classifier: Programming Language :: Python :: 3.9
Classifier: Programming Language :: Python :: 3.10
Classifier: Operating System :: POSIX :: Linux
Requires-Python: >=3.7
License-File: LICENSE
Requires-Dist: pyvista
Requires-Dist: matplotlib
Requires-Dist: mcpl
Requires-Dist: scipy
Requires-Dist: h5py
